environment/environment.yml
notebooks/README.md
notebooks/data-acquisition.ipynb
notebooks/run_example.sh
notebooks/run_full_replication.sh
notebooks/shared.py
notebooks/data-processing/collapse-sliiders-to-seg.ipynb
notebooks/data-processing/create-diaz-pyCIAM-inputs.ipynb
notebooks/data-processing/slr/AR6.ipynb
notebooks/data-processing/slr/sweet.ipynb
notebooks/data-processing/slr/AR5/1-convert-mat-version.ipynb
notebooks/data-processing/slr/AR5/2-generate-projected-lsl.ipynb
notebooks/data-processing/slr/AR5/3-retrieve-num-gcms.ipynb
notebooks/data-processing/slr/AR5/4-process-localizesl-output.ipynb
notebooks/data-processing/slr/AR5/5-create-slr-quantile.ipynb
notebooks/data-processing/slr/AR5/README.md
notebooks/models/create-surge-lookup-tables.ipynb
notebooks/models/fit-movefactor.ipynb
notebooks/models/run-pyCIAM-diaz2016.ipynb
notebooks/models/run-pyCIAM-slrquantiles.ipynb
notebooks/nb_logs/data-acquisition.ipynb
notebooks/nb_logs/data-processing/slr/AR6.ipynb
notebooks/nb_logs/models/run-pyCIAM-slrquantiles.ipynb
notebooks/post-processing/pyCIAM-results-figures.ipynb
notebooks/post-processing/zenodo-upload.ipynb
pyCIAM/__init__.py
pyCIAM/constants.py
pyCIAM/io.py
pyCIAM/run.py
pyCIAM/utils.py
pyCIAM/surge/__init__.py
pyCIAM/surge/_calc.py
pyCIAM/surge/damage_funcs.py
pyCIAM/surge/lookup.py
python_ciam-1.4.dist-info/licenses/LICENSE
python_ciam-1.4.dist-info/METADATA
python_ciam-1.4.dist-info/WHEEL
python_ciam-1.4.dist-info/top_level.txt
python_ciam-1.4.dist-info/RECORD
