Metadata-Version: 2.4
Name: python-CIAM
Version: 1.4
Summary: An efficient Python implementation of the Coastal Impacts and Adaptation Model (CIAM)
Author-email: Ian Bolliger <ian@reask.earth>, Nicholas Depsky <nicholas.depsky@undp.org>
Maintainer-email: Ian Bolliger <ian@reask.earth>
Project-URL: Homepage, https://github.com/ClimateImpactLab/pyCIAM
Classifier: Programming Language :: Python :: 3
Classifier: License :: OSI Approved :: MIT License
Classifier: Operating System :: OS Independent
Requires-Python: >=3.6
License-File: LICENSE
Requires-Dist: cloudpathlib
Requires-Dist: gitpython
Requires-Dist: rhg_compute_tools
Requires-Dist: parameterize_jobs
Requires-Dist: pint-xarray
Requires-Dist: scikit-learn
Requires-Dist: xarray[accel,parallel]
Requires-Dist: zarr
Dynamic: license-file
